nitrous_ema/__init__.py
nitrous_ema/ema.py
nitrous_ema-0.0.1.dist-info/METADATA
nitrous_ema-0.0.1.dist-info/WHEEL
nitrous_ema-0.0.1.dist-info/licenses/LICENSE
nitrous_ema-0.0.1.dist-info/RECORD
