Metadata-Version: 2.3
Name: nitrous_ema
Version: 0.0.1
Summary: Fast and simple post-hoc EMA (Karras et al., 2023) with minimal `.item()` calls.
Project-URL: Homepage, https://github.com/hkchengrex/nitrous-ema
Project-URL: Issues, https://github.com/hkchengrex/nitrous-ema/issues
Author-email: Rex Cheng <hkchengrex@gmail.com>
License-File: LICENSE
Classifier: Operating System :: OS Independent
Classifier: Programming Language :: Python :: 3
Requires-Python: >=3.9
Requires-Dist: torch>=2.0
